iranlowo/__init__.py
iranlowo/adr.py
iranlowo/compute_top_ngrams.py
iranlowo/web_scrape_bibeli.py
iranlowo/models/yo_adr_soft_attention_release.pt
onmt/__init__.py
onmt/model_builder.py
onmt/opts.py
onmt/trainer.py
onmt/decoders/__init__.py
onmt/decoders/cnn_decoder.py
onmt/decoders/decoder.py
onmt/decoders/ensemble.py
onmt/decoders/transformer.py
onmt/encoders/__init__.py
onmt/encoders/audio_encoder.py
onmt/encoders/cnn_encoder.py
onmt/encoders/encoder.py
onmt/encoders/image_encoder.py
onmt/encoders/mean_encoder.py
onmt/encoders/rnn_encoder.py
onmt/encoders/transformer.py
onmt/inputters/__init__.py
onmt/inputters/audio_dataset.py
onmt/inputters/datareader_base.py
onmt/inputters/dataset_base.py
onmt/inputters/image_dataset.py
onmt/inputters/inputter.py
onmt/inputters/text_dataset.py
onmt/models/__init__.py
onmt/models/model.py
onmt/models/model_saver.py
onmt/models/sru.py
onmt/models/stacked_rnn.py
onmt/modules/__init__.py
onmt/modules/average_attn.py
onmt/modules/conv_multi_step_attention.py
onmt/modules/copy_generator.py
onmt/modules/embeddings.py
onmt/modules/gate.py
onmt/modules/global_attention.py
onmt/modules/multi_headed_attn.py
onmt/modules/position_ffn.py
onmt/modules/sparse_activations.py
onmt/modules/sparse_losses.py
onmt/modules/structured_attention.py
onmt/modules/util_class.py
onmt/modules/weight_norm.py
onmt/translate/__init__.py
onmt/translate/beam.py
onmt/translate/beam_search.py
onmt/translate/decode_strategy.py
onmt/translate/penalties.py
onmt/translate/random_sampling.py
onmt/translate/translation.py
onmt/translate/translation_server.py
onmt/translate/translator.py
onmt/utils/__init__.py
onmt/utils/cnn_factory.py
onmt/utils/distributed.py
onmt/utils/earlystopping.py
onmt/utils/logging.py
onmt/utils/loss.py
onmt/utils/misc.py
onmt/utils/optimizers.py
onmt/utils/parse.py
onmt/utils/report_manager.py
onmt/utils/rnn_factory.py
onmt/utils/statistics.py
torchtext/__init__.py
torchtext/utils.py
torchtext/vocab.py
torchtext/data/__init__.py
iranlowo-0.0.8.3.dist-info/LICENSE
iranlowo-0.0.8.3.dist-info/METADATA
iranlowo-0.0.8.3.dist-info/WHEEL
iranlowo-0.0.8.3.dist-info/top_level.txt
iranlowo-0.0.8.3.dist-info/RECORD
