Metadata-Version: 2.1
Name: iranlowo
Version: 0.0.8.3
Summary: Utility library for analysis & (pre)processing of Yorùbá text
Home-page: https://github.com/Niger-Volta-LTI/iranlowo
Author: Ruoho Ruotsi
Author-email: ruoho.ruotsi@gmail.com
License: MIT
Download-URL: https://github.com/Niger-Volta-LTI/iranlowo/archive/v0.0.8.3.tar.gz
Platform: UNKNOWN
Classifier: Development Status :: 3 - Alpha
Classifier: Environment :: Console
Classifier: Intended Audience :: Developers
Classifier: License :: OSI Approved :: MIT License
Classifier: Operating System :: MacOS :: MacOS X
Classifier: Operating System :: POSIX
Classifier: Operating System :: Unix
Classifier: Programming Language :: Python
Classifier: Programming Language :: Python :: 3
Classifier: Programming Language :: Python :: 3.5
Classifier: Programming Language :: Python :: 3.6
Classifier: Programming Language :: Python :: 3.7
Classifier: Programming Language :: Python :: Implementation :: CPython
Classifier: Topic :: Software Development
Classifier: Topic :: Utilities
Requires-Dist: bs4
Requires-Dist: configargparse
Requires-Dist: torch
Requires-Dist: numpy
Requires-Dist: requests
Requires-Dist: tqdm
